{
    "diagnostic.errorSign": "",
    "diagnostic.warningSign": "",
    "diagnostic.infoSign": "",

    "explorer.width": 35,
    "exlorer.icon.enableVimDevicons": true,
    "explorer.icon.enableNerdfont": true,
    "explorer.keyMappings": {
    },
    "explorer.file.child.template": "[git | 2] [selection | clip | 1] [indent][icon | 1] [diagnosticError & 1][filename omitCenter 1][modified][readonly] [linkIcon & 1][link growRight 1 omitCenter 5]",
    "explorer.buffer.root.template": "[icon & 1] BUFFER",
    "explorer.file.root.template": "[icon & 1] FILE ([root])",
    "explorer.previewAction.onHover": true,
    "explorer.git.icon.status.ignored": "",
    "explorer.git.icon.status.untracked": "",
    "explorer.git.icon.status.added": "",
    "explorer.git.icon.status.modified": "",
    "explorer.git.icon.status.mixed": "",
    "explorer.keyMappings.global": {
      "i": false,
      "<c-o>": "noop",
  
      "*": "toggleSelection",
      "<tab>": "actionMenu",
  
      "gk": ["wait", "expandablePrev"],
      "gj": ["wait", "expandableNext"],
      "h": ["wait", "collapse"],
      "l": ["wait", "expandable?", "expand", "open"],
      "J": ["wait", "toggleSelection", "normal:j"],
      "K": ["wait", "toggleSelection", "normal:k"],
      "gl": ["wait", "expand:recursive"],
      "gh": ["wait", "collapse:recursive"],
      "<2-LeftMouse>": [
        "expandable?",
        ["expanded?", "collapse", "expand"],
        "open"
      ],
      "<cr>": ["wait", "expandable?", "cd", "open"],
      "o": ["wait", "expandable?", ["expanded?", "collapse", "expand"], "open"],
      "e": "open",
      "E": "open:split",
      "s": "open:vsplit",
      "t": "open:tab",
      "u": ["wait", "gotoParent"],
      "gs": ["wait", "reveal:select"],
      "zl": "preview:labeling",
      "zc": "preview:content",
      "Zl": "previewOnHover:toggle:labeling",
      "Zc": "previewOnHover:toggle:content",
      "ZI": "previewOnHover:disable",
  
      "yp": "copyFilepath",
      "yn": "copyFilename",
      "yy": "copyFile",
      "dd": "cutFile",
      "p": "pasteFile",
      "df": "delete",
      "dF": "deleteForever",
  
      "a": "addFile",
      "A": "addDirectory",
      "r": "rename",
  
      "I": "toggleHidden",
      "g<dot>": "toggleHidden",
      "R": "refresh",
  
      "?": "help",
      "q": "quit",
      "<esc>": "esc",
      "X": "systemExecute",
      "gd": "listDrive",
  
      "f": "search",
      "F": "searchRecursive",
  
      "gf": "gotoSource:file",
      "gb": "gotoSource:buffer",
  
      "[[": ["wait", "sourcePrev"],
      "]]": ["wait", "sourceNext"],
  
      "[i": ["wait", "indentPrev"],
      "]i": ["wait", "indentNext"],
  
      "[m": ["wait", "markPrev:modified"],
      "]m": ["wait", "markNext:modified"],
  
      "[d": ["wait", "markPrev:diagnosticError:diagnosticWarning"],
      "]d": ["wait", "markNext:diagnosticError:diagnosticWarning"],
      "[D": ["wait", "markPrev:diagnosticError"],
      "]D": ["wait", "markNext:diagnosticError"],
  
      "[c": ["wait", "markPrev:git"],
      "]c": ["wait", "markNext:git"],
      "<<": "gitStage",
      ">>": "gitUnstage"
    },
      "suggest.completionItemKindLabels": {
    "keyword":  "\uf1de", //  sliders
    "variable": "\ue79b", //  isometric box
    "value": "\uf89f", //  digits 123
    "operator": "\u03a8", // Ψ greek letter psi
    "constructor": "\uf0ad", //  wrench
    "function": "\u0192", // ƒ latin small letter F
    "reference": "\ufa46", // 渚 retweet symbol
    "constant": "\uf8fe", //  greek letter pi
    "method": "\uf09a", //  facebook "f"
    "struct": "\ufb44", // פּ file tree
    "class": "\uf0e8", //  hierarchy / site map
    "interface": "\uf417", //  git commit / line interrupted by circle
    "text": "\ue612", //  left-justified lines
    "enum": "\uf02c", //  pair of tags
    "enumMember": "\uf02b", //  tag
    "module": "\uf40d", //  code file / page showing angle brackets
    "color": "\ue22b", //  palette
    "property": "\ue624", //  predator dots
    "field": "\uf9be", // 料left-justified sorted lines
    "unit": "\uf475", //  negative-space ellipsis
    "event": "\ufacd", // 鬒clock alert / clock with exclamation mark
    "file": "\uf15b", //  file / blank page
    "folder": "\uf07b", //  folder
    "snippet": "\ue60b", //  pair of curly braces
    "typeParameter": "\uf728", //  file presentation box
    "default": "\uf29c" //  question mark in circle
  }
}
